src/__init__.py
src/cli.py
src/exporters/__init__.py
src/exporters/base_exporter.py
src/exporters/csv_exporter.py
src/exporters/json_exporter.py
src/exporters/mssql_exporter.py
src/exporters/mysql_exporter.py
src/exporters/oracle_exporter.py
src/exporters/orc_exporter.py
src/exporters/parquet_exporter.py
src/exporters/utils/__init__.py
src/exporters/utils/chunker.py
src/exporters/utils/constants.py
src/exporters/utils/exporter_config.py
src/exporters/utils/formatters.py
src/generator.py
src/providers/__init__.py
src/providers/base.py
src/providers/faker_provider.py
src/providers/mimesis_provider.py
src/schemas.py
testdatax-0.1.3.dist-info/LICENSE
testdatax-0.1.3.dist-info/METADATA
testdatax-0.1.3.dist-info/WHEEL
testdatax-0.1.3.dist-info/entry_points.txt
testdatax-0.1.3.dist-info/RECORD
