Metadata-Version: 2.3
Name: TestDataX
Version: 0.1.3
Summary: A flexible test data generation toolkit
License: MIT
Author: JamesPBrett
Requires-Python: >=3.11,<4.0
Classifier: License :: OSI Approved :: MIT License
Classifier: Programming Language :: Python :: 3
Classifier: Programming Language :: Python :: 3.11
Classifier: Programming Language :: Python :: 3.12
Classifier: Programming Language :: Python :: 3.13
Requires-Dist: faker (>=33.1.0,<34.0.0)
Requires-Dist: mimesis (>=18.0.0,<19.0.0)
Requires-Dist: mysql-connector-python (>=9.1.0,<10.0.0)
Requires-Dist: orjson (>=3.10.12,<4.0.0)
Requires-Dist: pandas (>=2.2.3,<3.0.0)
Requires-Dist: pyarrow (>=18.1.0,<19.0.0)
Requires-Dist: pydantic (>=2.10.4,<3.0.0)
Requires-Dist: typer (>=0.15.1,<0.16.0)
